MANIFEST.in
README.rst
setup.cfg
setup.py
src/colab_noosfero/__init__.py
src/colab_noosfero/apps.py
src/colab_noosfero/data_importer.py
src/colab_noosfero/diazo.xml
src/colab_noosfero/filters.py
src/colab_noosfero/models.py
src/colab_noosfero/search_indexes.py
src/colab_noosfero/signals.py
src/colab_noosfero/tasks.py
src/colab_noosfero/urls.py
src/colab_noosfero/views.py
src/colab_noosfero.egg-info/PKG-INFO
src/colab_noosfero.egg-info/SOURCES.txt
src/colab_noosfero.egg-info/dependency_links.txt
src/colab_noosfero.egg-info/not-zip-safe
src/colab_noosfero.egg-info/requires.txt
src/colab_noosfero.egg-info/top_level.txt
src/colab_noosfero/locale/en/LC_MESSAGES/django.mo
src/colab_noosfero/locale/en/LC_MESSAGES/django.po
src/colab_noosfero/locale/pt_BR/LC_MESSAGES/django.mo
src/colab_noosfero/locale/pt_BR/LC_MESSAGES/django.po
src/colab_noosfero/migrations/0001_initial.py
src/colab_noosfero/migrations/0002_auto_20151006_1811.py
src/colab_noosfero/migrations/0003_auto_20151006_1946.py
src/colab_noosfero/migrations/0004_auto_20151112_1322.py
src/colab_noosfero/migrations/0005_auto_20151123_1816.py
src/colab_noosfero/migrations/0006_remove_noosferosoftwareadmin_user.py
src/colab_noosfero/migrations/0007_noosferosoftwarecommunity.py
src/colab_noosfero/migrations/0008_noosferosoftwareadmin_username.py
src/colab_noosfero/migrations/__init__.py
src/colab_noosfero/static/noosfero/css/bootstrap-colab-style.css
src/colab_noosfero/static/noosfero/css/screen.css
src/colab_noosfero/static/noosfero/js/bootstrap.min.js
src/colab_noosfero/static/noosfero/js/colab_integration.js
src/colab_noosfero/templates/dashboard/articles_search_preview.html
src/colab_noosfero/templates/dashboard/community_search_preview.html
src/colab_noosfero/templates/proxy/noosfero.html
src/colab_noosfero/templates/search/articles_search_preview.html
src/colab_noosfero/templates/search/community_search_preview.html
src/colab_noosfero/templates/search/software_community_search_preview.html
src/colab_noosfero/templates/search/indexes/colab_noosfero/noosferoarticle_text.txt
src/colab_noosfero/templates/search/indexes/colab_noosfero/noosferocommunity_text.txt
src/colab_noosfero/templates/search/indexes/colab_noosfero/noosferosoftwarecommunity_text.txt
