Metadata-Version: 1.1
Name: colab-noosfero
Version: 0.2.7
Summary: A Noosfero plugin for Colab
Home-page: https://github.com/colab/colab-noosfero-plugin
Author: Sergio Oliveira
Author-email: sergio@tracy.com.br
License: GPLv3
Platform: UNKNOWN
Classifier: Framework :: Django
Classifier: Intended Audience :: Developers
Classifier: Intended Audience :: System Administrators
Classifier: Operating System :: OS Independent
Classifier: Topic :: Software Development
